LICENSE
README.md
setup.py
galileo_jupyter.egg-info/PKG-INFO
galileo_jupyter.egg-info/SOURCES.txt
galileo_jupyter.egg-info/dependency_links.txt
galileo_jupyter.egg-info/requires.txt
galileo_jupyter.egg-info/top_level.txt
galileojp/__init__.py
galileojp/env.py
galileojp/faassim.py
galileojp/faassiminmemory.py
galileojp/frames.py
galileojp/k3s.py
galileojp/local.py
galileojp/ml.py
galileojp/munger.py
galileojp/widgets.py
tests/__init__.py
tests/faassim/__init__.py
tests/faassim/test_faassim.py