Metadata-Version: 2.1
Name: galileo-jupyter
Version: 0.0.2.dev21
Summary: Galileo Jupyter: Tools for analyzing galileo experiments
Home-page: https://github.com/edgerun/galileo-jupyter
Author: Thomas Rausch, Philipp Raith
Author-email: t.rausch@dsg.tuwien.ac.at, p.raith@dsg.tuwien.ac.at
Classifier: Programming Language :: Python :: 3
Classifier: Operating System :: OS Independent
License-File: LICENSE
